rmdirs/__init__.py
rmdirs/__main__.py
rmdirs/utils.py
rmdirs-0.1.1.dist-info/LICENCE
rmdirs-0.1.1.dist-info/METADATA
rmdirs-0.1.1.dist-info/WHEEL
rmdirs-0.1.1.dist-info/top_level.txt
rmdirs-0.1.1.dist-info/RECORD
