Metadata-Version: 2.1
Name: rmdirs
Version: 0.1.1
Summary: Python utility for removing all subdirectories of a directory while preserving all the files located in the subdirectories.
Home-page: https://github.com/A-Bak/remove-dirs
Author: A-Bak
Author-email: adam.bak753@gmail.com
License: UNKNOWN
Keywords: utility util file-system file-structure remove-directories remove-dirs
Platform: UNKNOWN
Classifier: Programming Language :: Python :: 3
Classifier: License :: OSI Approved :: MIT License
Classifier: Operating System :: OS Independent
Requires-Python: >=3.6
